webconnect/__init__.py
webconnect-0.0.1.data/scripts/webconnectcli
webconnect-0.0.1.dist-info/LICENSE
webconnect-0.0.1.dist-info/METADATA
webconnect-0.0.1.dist-info/WHEEL
webconnect-0.0.1.dist-info/top_level.txt
webconnect-0.0.1.dist-info/RECORD
