Metadata-Version: 2.1
Name: webconnect
Version: 0.0.1
Summary: A simple tool to publish websites to RStudio Connect
Home-page: https://github.com/sellorm/webconnect
Author: Mark Sellors
Author-email: python@5vcc.com
License: UNKNOWN
Platform: UNKNOWN
Classifier: Programming Language :: Python :: 3
Classifier: License :: OSI Approved :: MIT License
Classifier: Operating System :: OS Independent
Requires-Python: >=3.6
Requires-Dist: requests
Requires-Dist: importlib-metadata (~=1.0) ; python_version < "3.8"
